tinyagent/__init__.py
tinyagent/base.py
tinyagent/schema.py
tinyagent/utils.py
tinyagent/common/__init__.py
tinyagent/common/event.py
tinyagent/common/time.py
tinyagent/llm/__init__.py
tinyagent/llm/claude/__init__.py
tinyagent/llm/claude/agent.py
tinyagent/llm/claude/client.py
tinyagent/llm/claude/schema.py
tinyagent/llm/gemini/__init__.py
tinyagent/llm/gemini/agent.py
tinyagent/llm/gemini/client.py
tinyagent/llm/gemini/schema.py
tinyagent/llm/gpt/__init__.py
tinyagent/llm/gpt/agent.py
tinyagent/llm/gpt/client.py
tinyagent/llm/gpt/schema.py
tinyagent/tools/__init__.py
tinyagent/tools/calculator.py
tinyagent/tools/current_time.py
tinyagent/tools/tavily.py
tinyagent/tools/tool.py
tinyagent-0.2.4.dist-info/LICENSE
tinyagent-0.2.4.dist-info/METADATA
tinyagent-0.2.4.dist-info/WHEEL
tinyagent-0.2.4.dist-info/top_level.txt
tinyagent-0.2.4.dist-info/RECORD
