Metadata-Version: 2.1
Name: tinyagent
Version: 0.2.4
Summary: A minimalistic agent framework
Home-page: https://github.com/y-lan/tinyagent
Author: y-lan
Author-email: lanyuyang@gmail.com
License: UNKNOWN
Platform: UNKNOWN
Classifier: Programming Language :: Python :: 3
Classifier: License :: OSI Approved :: MIT License
Classifier: Operating System :: OS Independent
Requires-Python: >=3.10
License-File: LICENSE
Requires-Dist: pydantic>=2.7.1
Requires-Dist: requests>=2.31.0
